InfluxdbJianmingShouce/README.md
InfluxdbJianmingShouce/__init__.py
InfluxdbJianmingShouce/__main__.py
InfluxdbJianmingShouce/file.epub
InfluxdbJianmingShouce/index.html
InfluxdbJianmingShouce/css/__init__.py
InfluxdbJianmingShouce/css/annotations.css
InfluxdbJianmingShouce/css/main.css
InfluxdbJianmingShouce/css/normalize.css
InfluxdbJianmingShouce/css/popup.css
InfluxdbJianmingShouce/font/__init__.py
InfluxdbJianmingShouce/font/fontello.eot
InfluxdbJianmingShouce/font/fontello.svg
InfluxdbJianmingShouce/font/fontello.ttf
InfluxdbJianmingShouce/font/fontello.woff
InfluxdbJianmingShouce/img/__init__.py
InfluxdbJianmingShouce/img/annotator-glyph-sprite.png
InfluxdbJianmingShouce/img/annotator-icon-sprite.png
InfluxdbJianmingShouce/img/apple-touch-icon.png
InfluxdbJianmingShouce/img/cancelfullscreen.png
InfluxdbJianmingShouce/img/close.png
InfluxdbJianmingShouce/img/fullscreen.png
InfluxdbJianmingShouce/img/loader.gif
InfluxdbJianmingShouce/img/menu-icon.png
InfluxdbJianmingShouce/img/save.png
InfluxdbJianmingShouce/img/saved.png
InfluxdbJianmingShouce/img/settings-s.png
InfluxdbJianmingShouce/img/settings.png
InfluxdbJianmingShouce/img/star.png
InfluxdbJianmingShouce/js/__init__.py
InfluxdbJianmingShouce/js/epub.js
InfluxdbJianmingShouce/js/epub.min.js
InfluxdbJianmingShouce/js/epub.min.map
InfluxdbJianmingShouce/js/hooks.min.js
InfluxdbJianmingShouce/js/hooks.min.map
InfluxdbJianmingShouce/js/reader.js
InfluxdbJianmingShouce/js/reader.js.map
InfluxdbJianmingShouce/js/reader.min.js
InfluxdbJianmingShouce/js/reader.min.map
InfluxdbJianmingShouce/js/hooks/__init__.py
InfluxdbJianmingShouce/js/hooks/extensions/__init__.py
InfluxdbJianmingShouce/js/hooks/extensions/highlight.js
InfluxdbJianmingShouce/js/libs/__init__.py
InfluxdbJianmingShouce/js/libs/jquery.min.js
InfluxdbJianmingShouce/js/libs/localforage.min.js
InfluxdbJianmingShouce/js/libs/screenfull.js
InfluxdbJianmingShouce/js/libs/screenfull.min.js
InfluxdbJianmingShouce/js/libs/zip.min.js
influxdb_jianming_shouce-2024.3.4.0.dist-info/METADATA
influxdb_jianming_shouce-2024.3.4.0.dist-info/WHEEL
influxdb_jianming_shouce-2024.3.4.0.dist-info/entry_points.txt
influxdb_jianming_shouce-2024.3.4.0.dist-info/top_level.txt
influxdb_jianming_shouce-2024.3.4.0.dist-info/RECORD
